[{"name": "car", "cam": 0, "filenames": ["0_car_1565266123_0206118.jpg"], "x": 1565266145, "text": ["0_car_1565266123_0206118.jpg"], "y": 1}, {"name": "car", "cam": 2, "filenames": ["2_car_1565266127_780705.jpg"], "x": 1565266150, "text": ["2_car_1565266127_780705.jpg"], "y": 1}, {"name": "car", "cam": 0, "filenames": ["0_car_1565266123_0206118.jpg"], "x": 1565266152, "text": ["0_car_1565266123_0206118.jpg"], "y": 1}, {"name": "car", "cam": 2, "filenames": ["2_car_1565266127_780705.jpg"], "x": 1565266157, "text": ["2_car_1565266127_780705.jpg"], "y": 1}, {"name": "car", "cam": 0, "filenames": ["0_car_1565266123_0206118.jpg"], "x": 1565266159, "text": ["0_car_1565266123_0206118.jpg"], "y": 1}, {"name": "car", "cam": 2, "filenames": ["2_car_1565266127_780705.jpg"], "x": 1565266165, "text": ["2_car_1565266127_780705.jpg"], "y": 1}, {"name": "car", "cam": 0, "filenames": ["0_car_1565266123_0206118.jpg"], "x": 1565266167, "text": ["0_car_1565266123_0206118.jpg"], "y": 1}, {"name": "car", "cam": 2, "filenames": ["2_car_1565266127_780705.jpg"], "x": 1565266172, "text": ["2_car_1565266127_780705.jpg"], "y": 1}, {"name": "car", "cam": 0, "filenames": ["0_car_1565266123_0206118.jpg"], "x": 1565266175, "text": ["0_car_1565266123_0206118.jpg"], "y": 2}, {"name": "car", "cam": 2, "filenames": ["2_car_1565266127_780705.jpg"], "x": 1565266179, "text": ["2_car_1565266127_780705.jpg"], "y": 1}, {"name": "car", "cam": 0, "filenames": ["0_car_1565266123_0206118.jpg"], "x": 1565266182, "text": ["0_car_1565266123_0206118.jpg"], "y": 2}, {"name": "car", "cam": 2, "filenames": ["2_car_1565266127_780705.jpg"], "x": 1565266187, "text": ["2_car_1565266127_780705.jpg"], "y": 1}, {"name": "car", "cam": 0, "filenames": ["0_car_1565266123_0206118.jpg"], "x": 1565266189, "text": ["0_car_1565266123_0206118.jpg"], "y": 2}, {"name": "car", "cam": 2, "filenames": ["2_car_1565266127_780705.jpg"], "x": 1565266194, "text": ["2_car_1565266127_780705.jpg"], "y": 1}, {"name": "car", "cam": 0, "filenames": ["0_car_1565266196_9166825.jpg"], "x": 1565266196, "text": ["0_car_1565266196_9166825.jpg"], "y": 2}, {"name": "car", "cam": 2, "filenames": ["2_car_1565266201_8465352.jpg"], "x": 1565266201, "text": ["2_car_1565266201_8465352.jpg"], "y": 1}, {"name": "car", "cam": 0, "filenames": ["0_car_1565266196_9166825.jpg"], "x": 1565266204, "text": ["0_car_1565266196_9166825.jpg"], "y": 2}, {"name": "car", "cam": 2, "filenames": ["2_car_1565266201_8465352.jpg"], "x": 1565266208, "text": ["2_car_1565266201_8465352.jpg"], "y": 1}, {"name": "car", "cam": 0, "filenames": ["0_car_1565266196_9166825.jpg"], "x": 1565266211, "text": ["0_car_1565266196_9166825.jpg"], "y": 2}, {"name": "car", "cam": 2, "filenames": ["2_car_1565266201_8465352.jpg"], "x": 1565266216, "text": ["2_car_1565266201_8465352.jpg"], "y": 1}, {"name": "car", "cam": 0, "filenames": ["0_car_1565266196_9166825.jpg"], "x": 1565266218, "text": ["0_car_1565266196_9166825.jpg"], "y": 2}, {"name": "car", "cam": 2, "filenames": ["2_car_1565266201_8465352.jpg"], "x": 1565266223, "text": ["2_car_1565266201_8465352.jpg"], "y": 1}, {"name": "car", "cam": 0, "filenames": ["0_car_1565266196_9166825.jpg"], "x": 1565266226, "text": ["0_car_1565266196_9166825.jpg"], "y": 2}, {"name": "car", "cam": 2, "filenames": ["2_car_1565266201_8465352.jpg"], "x": 1565266231, "text": ["2_car_1565266201_8465352.jpg"], "y": 1}, {"name": "car", "cam": 0, "filenames": ["0_car_1565266196_9166825.jpg"], "x": 1565266234, "text": ["0_car_1565266196_9166825.jpg"], "y": 2}, {"name": "car", "cam": 2, "filenames": ["2_car_1565266201_8465352.jpg"], "x": 1565266238, "text": ["2_car_1565266201_8465352.jpg"], "y": 1}, {"name": "car", "cam": 0, "filenames": ["0_car_1565266196_9166825.jpg"], "x": 1565266241, "text": ["0_car_1565266196_9166825.jpg"], "y": 2}, {"name": "car", "cam": 2, "filenames": ["2_car_1565266201_8465352.jpg"], "x": 1565266246, "text": ["2_car_1565266201_8465352.jpg"], "y": 1}, {"name": "car", "cam": 0, "filenames": ["0_car_1565266196_9166825.jpg"], "x": 1565266248, "text": ["0_car_1565266196_9166825.jpg"], "y": 2}, {"name": "car", "cam": 2, "filenames": ["2_car_1565266201_8465352.jpg"], "x": 1565266253, "text": ["2_car_1565266201_8465352.jpg"], "y": 1}, {"name": "car", "cam": 0, "filenames": ["0_car_1565266196_9166825.jpg"], "x": 1565266255, "text": ["0_car_1565266196_9166825.jpg"], "y": 2}, {"name": "car", "cam": 2, "filenames": ["2_car_1565266201_8465352.jpg"], "x": 1565266260, "text": ["2_car_1565266201_8465352.jpg"], "y": 1}, {"name": "car", "cam": 0, "filenames": ["0_car_1565266196_9166825.jpg"], "x": 1565266263, "text": ["0_car_1565266196_9166825.jpg"], "y": 2}, {"name": "car", "cam": 2, "filenames": ["2_car_1565266201_8465352.jpg"], "x": 1565266268, "text": ["2_car_1565266201_8465352.jpg"], "y": 1}, {"name": "car", "cam": 0, "filenames": ["0_car_1565266270_8491552.jpg"], "x": 1565266270, "text": ["0_car_1565266270_8491552.jpg"], "y": 2}, {"name": "car", "cam": 2, "filenames": ["2_car_1565266275_970316.jpg"], "x": 1565266275, "text": ["2_car_1565266275_970316.jpg"], "y": 1}, {"name": "car", "cam": 0, "filenames": ["0_car_1565266270_8491552.jpg"], "x": 1565266278, "text": ["0_car_1565266270_8491552.jpg"], "y": 2}, {"name": "car", "cam": 2, "filenames": ["2_car_1565266275_970316.jpg"], "x": 1565266283, "text": ["2_car_1565266275_970316.jpg"], "y": 1}, {"name": "car", "cam": 0, "filenames": ["0_car_1565266270_8491552.jpg"], "x": 1565266286, "text": ["0_car_1565266270_8491552.jpg"], "y": 2}, {"name": "car", "cam": 2, "filenames": ["2_car_1565266275_970316.jpg"], "x": 1565266290, "text": ["2_car_1565266275_970316.jpg"], "y": 1}, {"name": "car", "cam": 0, "filenames": ["0_car_1565266270_8491552.jpg"], "x": 1565266293, "text": ["0_car_1565266270_8491552.jpg"], "y": 2}, {"name": "car", "cam": 2, "filenames": ["2_car_1565266275_970316.jpg"], "x": 1565266298, "text": ["2_car_1565266275_970316.jpg"], "y": 1}, {"name": "car", "cam": 0, "filenames": ["0_car_1565266270_8491552.jpg"], "x": 1565266300, "text": ["0_car_1565266270_8491552.jpg"], "y": 2}, {"name": "car", "cam": 2, "filenames": ["2_car_1565266275_970316.jpg"], "x": 1565266305, "text": ["2_car_1565266275_970316.jpg"], "y": 1}, {"name": "car", "cam": 0, "filenames": ["0_car_1565266270_8491552.jpg"], "x": 1565266308, "text": ["0_car_1565266270_8491552.jpg"], "y": 2}, {"name": "car", "cam": 2, "filenames": ["2_car_1565266275_970316.jpg"], "x": 1565266313, "text": ["2_car_1565266275_970316.jpg"], "y": 1}, {"name": "car", "cam": 0, "filenames": ["0_car_1565266270_8491552.jpg"], "x": 1565266316, "text": ["0_car_1565266270_8491552.jpg"], "y": 2}, {"name": "car", "cam": 2, "filenames": ["2_car_1565266275_970316.jpg"], "x": 1565266320, "text": ["2_car_1565266275_970316.jpg"], "y": 1}, {"name": "car", "cam": 0, "filenames": ["0_car_1565266270_8491552.jpg"], "x": 1565266323, "text": ["0_car_1565266270_8491552.jpg"], "y": 2}, {"name": "car", "cam": 2, "filenames": ["2_car_1565266275_970316.jpg"], "x": 1565266328, "text": ["2_car_1565266275_970316.jpg"], "y": 1}, {"name": "car", "cam": 0, "filenames": ["0_car_1565266270_8491552.jpg"], "x": 1565266330, "text": ["0_car_1565266270_8491552.jpg"], "y": 2}, {"name": "car", "cam": 2, "filenames": ["2_car_1565266275_970316.jpg"], "x": 1565266335, "text": ["2_car_1565266275_970316.jpg"], "y": 1}, {"name": "car", "cam": 0, "filenames": ["0_car_1565266270_8491552.jpg"], "x": 1565266338, "text": ["0_car_1565266270_8491552.jpg"], "y": 2}, {"name": "car", "cam": 2, "filenames": ["2_car_1565266275_970316.jpg"], "x": 1565266343, "text": ["2_car_1565266275_970316.jpg"], "y": 1}, {"name": "car", "cam": 0, "filenames": ["0_car_1565266345_6031039.jpg"], "x": 1565266345, "text": ["0_car_1565266345_6031039.jpg"], "y": 2}, {"name": "car", "cam": 2, "filenames": ["2_car_1565266350_6638641.jpg"], "x": 1565266350, "text": ["2_car_1565266350_6638641.jpg"], "y": 1}, {"name": "car", "cam": 0, "filenames": ["0_car_1565266345_6031039.jpg"], "x": 1565266353, "text": ["0_car_1565266345_6031039.jpg"], "y": 2}, {"name": "car", "cam": 2, "filenames": ["2_car_1565266350_6638641.jpg"], "x": 1565266357, "text": ["2_car_1565266350_6638641.jpg"], "y": 1}, {"name": "car", "cam": 0, "filenames": ["0_car_1565266345_6031039.jpg"], "x": 1565266360, "text": ["0_car_1565266345_6031039.jpg"], "y": 2}, {"name": "car", "cam": 2, "filenames": ["2_car_1565266350_6638641.jpg"], "x": 1565266365, "text": ["2_car_1565266350_6638641.jpg"], "y": 1}, {"name": "car", "cam": 0, "filenames": ["0_car_1565266345_6031039.jpg"], "x": 1565266367, "text": ["0_car_1565266345_6031039.jpg"], "y": 2}, {"name": "car", "cam": 2, "filenames": ["2_car_1565266350_6638641.jpg"], "x": 1565266372, "text": ["2_car_1565266350_6638641.jpg"], "y": 1}, {"name": "car", "cam": 0, "filenames": ["0_car_1565266345_6031039.jpg"], "x": 1565266375, "text": ["0_car_1565266345_6031039.jpg"], "y": 2}, {"name": "car", "cam": 2, "filenames": ["2_car_1565266350_6638641.jpg"], "x": 1565266380, "text": ["2_car_1565266350_6638641.jpg"], "y": 1}, {"name": "car", "cam": 0, "filenames": ["0_car_1565266345_6031039.jpg"], "x": 1565266382, "text": ["0_car_1565266345_6031039.jpg"], "y": 2}, {"name": "car", "cam": 2, "filenames": ["2_car_1565266350_6638641.jpg"], "x": 1565266387, "text": ["2_car_1565266350_6638641.jpg"], "y": 1}, {"name": "car", "cam": 0, "filenames": ["0_car_1565266345_6031039.jpg"], "x": 1565266389, "text": ["0_car_1565266345_6031039.jpg"], "y": 2}, {"name": "car", "cam": 2, "filenames": ["2_car_1565266350_6638641.jpg"], "x": 1565266394, "text": ["2_car_1565266350_6638641.jpg"], "y": 1}, {"name": "car", "cam": 0, "filenames": ["0_car_1565266345_6031039.jpg"], "x": 1565266397, "text": ["0_car_1565266345_6031039.jpg"], "y": 2}, {"name": "car", "cam": 2, "filenames": ["2_car_1565266350_6638641.jpg"], "x": 1565266402, "text": ["2_car_1565266350_6638641.jpg"], "y": 1}, {"name": "car", "cam": 0, "filenames": ["0_car_1565266345_6031039.jpg"], "x": 1565266404, "text": ["0_car_1565266345_6031039.jpg"], "y": 2}, {"name": "car", "cam": 2, "filenames": ["2_car_1565266350_6638641.jpg"], "x": 1565266409, "text": ["2_car_1565266350_6638641.jpg"], "y": 1}, {"name": "car", "cam": 0, "filenames": ["0_car_1565266345_6031039.jpg"], "x": 1565266412, "text": ["0_car_1565266345_6031039.jpg"], "y": 2}, {"name": "car", "cam": 2, "filenames": ["2_car_1565266350_6638641.jpg"], "x": 1565266417, "text": ["2_car_1565266350_6638641.jpg"], "y": 1}, {"name": "car", "cam": 0, "filenames": ["0_car_1565266419_6662078.jpg"], "x": 1565266419, "text": ["0_car_1565266419_6662078.jpg"], "y": 2}, {"name": "car", "cam": 2, "filenames": ["2_car_1565266424_7458158.jpg"], "x": 1565266424, "text": ["2_car_1565266424_7458158.jpg"], "y": 1}, {"name": "car", "cam": 0, "filenames": ["0_car_1565266419_6662078.jpg"], "x": 1565266427, "text": ["0_car_1565266419_6662078.jpg"], "y": 2}, {"name": "car", "cam": 2, "filenames": ["2_car_1565266424_7458158.jpg"], "x": 1565266432, "text": ["2_car_1565266424_7458158.jpg"], "y": 1}, {"name": "car", "cam": 0, "filenames": ["0_car_1565266419_6662078.jpg"], "x": 1565266434, "text": ["0_car_1565266419_6662078.jpg"], "y": 2}, {"name": "car", "cam": 2, "filenames": ["2_car_1565266424_7458158.jpg"], "x": 1565266439, "text": ["2_car_1565266424_7458158.jpg"], "y": 1}, {"name": "car", "cam": 0, "filenames": ["0_car_1565266419_6662078.jpg"], "x": 1565266441, "text": ["0_car_1565266419_6662078.jpg"], "y": 2}, {"name": "car", "cam": 2, "filenames": ["2_car_1565266424_7458158.jpg"], "x": 1565266446, "text": ["2_car_1565266424_7458158.jpg"], "y": 1}, {"name": "car", "cam": 0, "filenames": ["0_car_1565266419_6662078.jpg"], "x": 1565266449, "text": ["0_car_1565266419_6662078.jpg"], "y": 2}, {"name": "car", "cam": 2, "filenames": ["2_car_1565266424_7458158.jpg"], "x": 1565266454, "text": ["2_car_1565266424_7458158.jpg"], "y": 1}, {"name": "car", "cam": 0, "filenames": ["0_car_1565266419_6662078.jpg"], "x": 1565266457, "text": ["0_car_1565266419_6662078.jpg"], "y": 2}, {"name": "car", "cam": 2, "filenames": ["2_car_1565266424_7458158.jpg"], "x": 1565266462, "text": ["2_car_1565266424_7458158.jpg"], "y": 1}, {"name": "car", "cam": 0, "filenames": ["0_car_1565266419_6662078.jpg"], "x": 1565266464, "text": ["0_car_1565266419_6662078.jpg"], "y": 2}, {"name": "car", "cam": 2, "filenames": ["2_car_1565266424_7458158.jpg"], "x": 1565266469, "text": ["2_car_1565266424_7458158.jpg"], "y": 1}, {"name": "car", "cam": 0, "filenames": ["0_car_1565266419_6662078.jpg"], "x": 1565266471, "text": ["0_car_1565266419_6662078.jpg"], "y": 2}, {"name": "car", "cam": 2, "filenames": ["2_car_1565266424_7458158.jpg"], "x": 1565266476, "text": ["2_car_1565266424_7458158.jpg"], "y": 1}, {"name": "car", "cam": 0, "filenames": ["0_car_1565266419_6662078.jpg"], "x": 1565266479, "text": ["0_car_1565266419_6662078.jpg"], "y": 2}, {"name": "car", "cam": 2, "filenames": ["2_car_1565266424_7458158.jpg"], "x": 1565266483, "text": ["2_car_1565266424_7458158.jpg"], "y": 1}, {"name": "car", "cam": 0, "filenames": ["0_car_1565266419_6662078.jpg"], "x": 1565266486, "text": ["0_car_1565266419_6662078.jpg"], "y": 2}, {"name": "car", "cam": 2, "filenames": ["2_car_1565266424_7458158.jpg"], "x": 1565266490, "text": ["2_car_1565266424_7458158.jpg"], "y": 1}, {"name": "car", "cam": 0, "filenames": ["0_car_1565266493_3485248.jpg"], "x": 1565266493, "text": ["0_car_1565266493_3485248.jpg"], "y": 2}, {"name": "car", "cam": 2, "filenames": ["2_car_1565266498_2597184.jpg"], "x": 1565266498, "text": ["2_car_1565266498_2597184.jpg"], "y": 1}, {"name": "car", "cam": 0, "filenames": ["0_car_1565266493_3485248.jpg"], "x": 1565266500, "text": ["0_car_1565266493_3485248.jpg"], "y": 2}, {"name": "car", "cam": 2, "filenames": ["2_car_1565266498_2597184.jpg"], "x": 1565266505, "text": ["2_car_1565266498_2597184.jpg"], "y": 1}, {"name": "car", "cam": 0, "filenames": ["0_car_1565266493_3485248.jpg"], "x": 1565266508, "text": ["0_car_1565266493_3485248.jpg"], "y": 2}, {"name": "car", "cam": 2, "filenames": ["2_car_1565266498_2597184.jpg"], "x": 1565266512, "text": ["2_car_1565266498_2597184.jpg"], "y": 1}, {"name": "car", "cam": 0, "filenames": ["0_car_1565266493_3485248.jpg"], "x": 1565266515, "text": ["0_car_1565266493_3485248.jpg"], "y": 2}, {"name": "car", "cam": 2, "filenames": ["2_car_1565266498_2597184.jpg"], "x": 1565266520, "text": ["2_car_1565266498_2597184.jpg"], "y": 1}, {"name": "car", "cam": 0, "filenames": ["0_car_1565266493_3485248.jpg"], "x": 1565266522, "text": ["0_car_1565266493_3485248.jpg"], "y": 2}, {"name": "car", "cam": 2, "filenames": ["2_car_1565266498_2597184.jpg"], "x": 1565266527, "text": ["2_car_1565266498_2597184.jpg"], "y": 1}, {"name": "car", "cam": 0, "filenames": ["0_car_1565266493_3485248.jpg"], "x": 1565266530, "text": ["0_car_1565266493_3485248.jpg"], "y": 2}, {"name": "car", "cam": 2, "filenames": ["2_car_1565266498_2597184.jpg"], "x": 1565266535, "text": ["2_car_1565266498_2597184.jpg"], "y": 1}, {"name": "car", "cam": 0, "filenames": ["0_car_1565266493_3485248.jpg"], "x": 1565266537, "text": ["0_car_1565266493_3485248.jpg"], "y": 2}, {"name": "car", "cam": 2, "filenames": ["2_car_1565266498_2597184.jpg"], "x": 1565266542, "text": ["2_car_1565266498_2597184.jpg"], "y": 1}, {"name": "car", "cam": 0, "filenames": ["0_car_1565266493_3485248.jpg"], "x": 1565266545, "text": ["0_car_1565266493_3485248.jpg"], "y": 2}, {"name": "car", "cam": 2, "filenames": ["2_car_1565266498_2597184.jpg"], "x": 1565266549, "text": ["2_car_1565266498_2597184.jpg"], "y": 1}, {"name": "car", "cam": 0, "filenames": ["0_car_1565266493_3485248.jpg"], "x": 1565266552, "text": ["0_car_1565266493_3485248.jpg"], "y": 2}, {"name": "car", "cam": 2, "filenames": ["2_car_1565266498_2597184.jpg"], "x": 1565266557, "text": ["2_car_1565266498_2597184.jpg"], "y": 1}, {"name": "car", "cam": 0, "filenames": ["0_car_1565266493_3485248.jpg"], "x": 1565266559, "text": ["0_car_1565266493_3485248.jpg"], "y": 2}, {"name": "car", "cam": 2, "filenames": ["2_car_1565266498_2597184.jpg"], "x": 1565266564, "text": ["2_car_1565266498_2597184.jpg"], "y": 1}, {"name": "car", "cam": 0, "filenames": ["0_car_1565266567_2445688.jpg"], "x": 1565266567, "text": ["0_car_1565266567_2445688.jpg"], "y": 1}, {"name": "car", "cam": 2, "filenames": ["2_car_1565266572_1756527.jpg"], "x": 1565266572, "text": ["2_car_1565266572_1756527.jpg"], "y": 1}, {"name": "car", "cam": 0, "filenames": ["0_car_1565266567_2445688.jpg"], "x": 1565266574, "text": ["0_car_1565266567_2445688.jpg"], "y": 2}, {"name": "car", "cam": 2, "filenames": ["2_car_1565266572_1756527.jpg"], "x": 1565266579, "text": ["2_car_1565266572_1756527.jpg"], "y": 1}, {"name": "car", "cam": 0, "filenames": ["0_car_1565266567_2445688.jpg"], "x": 1565266582, "text": ["0_car_1565266567_2445688.jpg"], "y": 2}, {"name": "car", "cam": 2, "filenames": ["2_car_1565266572_1756527.jpg"], "x": 1565266587, "text": ["2_car_1565266572_1756527.jpg"], "y": 1}, {"name": "car", "cam": 0, "filenames": ["0_car_1565266567_2445688.jpg"], "x": 1565266589, "text": ["0_car_1565266567_2445688.jpg"], "y": 2}, {"name": "car", "cam": 2, "filenames": ["2_car_1565266572_1756527.jpg"], "x": 1565266594, "text": ["2_car_1565266572_1756527.jpg"], "y": 1}, {"name": "car", "cam": 0, "filenames": ["0_car_1565266567_2445688.jpg"], "x": 1565266597, "text": ["0_car_1565266567_2445688.jpg"], "y": 2}, {"name": "car", "cam": 2, "filenames": ["2_car_1565266572_1756527.jpg"], "x": 1565266602, "text": ["2_car_1565266572_1756527.jpg"], "y": 1}, {"name": "car", "cam": 0, "filenames": ["0_car_1565266567_2445688.jpg"], "x": 1565266604, "text": ["0_car_1565266567_2445688.jpg"], "y": 2}, {"name": "car", "cam": 2, "filenames": ["2_car_1565266572_1756527.jpg"], "x": 1565266609, "text": ["2_car_1565266572_1756527.jpg"], "y": 1}, {"name": "car", "cam": 0, "filenames": ["0_car_1565266567_2445688.jpg"], "x": 1565266611, "text": ["0_car_1565266567_2445688.jpg"], "y": 2}, {"name": "car", "cam": 2, "filenames": ["2_car_1565266572_1756527.jpg"], "x": 1565266616, "text": ["2_car_1565266572_1756527.jpg"], "y": 1}, {"name": "car", "cam": 0, "filenames": ["0_car_1565266567_2445688.jpg"], "x": 1565266618, "text": ["0_car_1565266567_2445688.jpg"], "y": 2}, {"name": "car", "cam": 2, "filenames": ["2_car_1565266572_1756527.jpg"], "x": 1565266624, "text": ["2_car_1565266572_1756527.jpg"], "y": 1}, {"name": "car", "cam": 0, "filenames": ["0_car_1565266567_2445688.jpg"], "x": 1565266626, "text": ["0_car_1565266567_2445688.jpg"], "y": 2}, {"name": "car", "cam": 2, "filenames": ["2_car_1565266572_1756527.jpg"], "x": 1565266631, "text": ["2_car_1565266572_1756527.jpg"], "y": 1}, {"name": "car", "cam": 0, "filenames": ["0_car_1565266567_2445688.jpg"], "x": 1565266634, "text": ["0_car_1565266567_2445688.jpg"], "y": 2}, {"name": "car", "cam": 2, "filenames": ["2_car_1565266572_1756527.jpg"], "x": 1565266638, "text": ["2_car_1565266572_1756527.jpg"], "y": 1}]